matrixops.v
module matrixops (
    input            clk,
    input            rst,
    input            enter,
    input      [1:0] X,
    input      [1:0] Y,
    output reg       Z
);

    // 3 states
    parameter IDLE = 2'b00;
    parameter in = 2'b01;
    parameter out = 2'b10;

    //internal variables
    reg [1:0] state;
    reg [2:0] cnt;
    reg [3:0] ent_cnt;
    reg [1:0] prev_Y;
    reg [1:0] prev_X;
    reg  prev_ent;
    reg prev_Z;

 
    // one dimensional matrix structure
    wire [3:0] index = {Y,X};
    reg [15:0] matrix;  
    
    //state transitions
    always @(posedge clk or posedge rst) begin
        if (rst) begin
            state <= IDLE;
            cnt <= 3'd0;
            matrix <= 16'b0;
        end else begin
            case (state)
                IDLE: begin
                    if (ent_cnt>=1) begin
                      state <= in;
                      if (enter) begin
                        matrix[index] <= 1'b1; //inserting the first element into matrix
                      end
                
                    end
                end

                in: begin
                    if (cnt < 3'd4 & enter) begin
                        matrix[index] <= 1'b1;  
                        
                    end else if (cnt >= 3'd4)begin
                        state <= out; 
                    end
                end

                out: begin end
            endcase
        end
    end
    
    // Counter implementation which counts the number of enters 
   always @(posedge clk or posedge rst) begin
    if(rst) begin
      ent_cnt <=3'b0;
    end else if (enter) begin
      ent_cnt<= ent_cnt+1;
    end
  end

  //Counter implementation which counts the number of inputs
  always @(posedge clk or posedge rst) begin
    if(rst) begin
        cnt <= 3'd0;
    end
    else if (enter) begin
        if (ent_cnt>= 4'd2) begin
            cnt <= cnt + 3'd1;
        end
    end
  end

  // Updating the previous values 
  always @(negedge clk) begin
    prev_Y<=Y;
    prev_X<=X;
    prev_ent<=enter;
  end

  wire [3:0] prev_idx = {prev_Y,prev_X};

  always @(negedge clk) begin
    if (state == out) begin
      prev_Z<=Z;
    end
  end
   
  // Deciding on output (Z value) by covering all transitions of enter from one phase to another
    always @(posedge clk or posedge rst) begin
        if (rst) begin
            Z <= 1'b0;
        end else if (((!prev_ent & !enter)|(enter==1&prev_ent==0))&(state == out)) begin 
            Z <= prev_Z;
        end else if (state == out & ((prev_ent ^ enter)|(prev_ent==1&enter==1))) begin
            
            Z <= matrix[prev_idx];
        end else begin
            Z <= 1'b0;
    end
end

endmodule

matrixops_tb.v
module matrixops_tb ();

  // Ports
  reg        clk  ;
  reg        rst  ;
  reg        enter;
  reg  [1:0] X    ;
  reg  [1:0] Y    ;
  wire       Z    ;

  // Instantiate the matrixops module (Device Under Test)
  matrixops dut (
    .clk  (clk  ),
    .rst  (rst  ),
    .enter(enter),
    .X    (X    ),
    .Y    (Y    ),
    .Z    (Z    )
  );

  // Half period of our clock signal
  parameter HP = 5;
  // Full period of our clock signal
  parameter FP = (2*HP);

  // Clock generation
  always #HP clk = ~clk;

  initial begin
    // Setup waveform dump
    $dumpfile("matrixops_tb.vcd");
    $dumpvars(0, matrixops_tb);

    $display("Simulation started.");

    // Initialize signals
    clk = 1;
    rst = 1;
    X = 0;
    Y = 0;
    enter = 0;
    #(FP-1); // To avoid race conditions, modify inputs prior to the clock edge

    rst = 0;
    X = 0;
    Y = 0;
    enter = 1;
    #FP;

    rst = 0;
    X = 0;
    Y = 0;
    enter = 0;
    #FP;

    rst = 0;
    X = 2;
    Y = 0;
    enter = 1;
    #FP;

    rst = 0;
    X = 1;
    Y = 1;
    enter = 1;
    #FP;

    rst = 0;
    X = 1;
    Y = 3;
    enter = 1;
    #FP;

    rst = 0;
    X = 1;
    Y = 3;
    enter = 1;
    #FP;

    rst = 0;
    X = 3;
    Y = 3;
    enter = 1;
    #FP;

    rst = 0;
    X = 0;
    Y = 2;
    enter = 1;
    #FP;

    rst = 0;
    X = 1;
    Y = 1;
    enter = 1;
    #FP;

    rst = 0;
    X = 1;
    Y = 1;
    enter = 0;
    #FP;

    rst = 0;
    X = 1;
    Y = 1;
    enter = 0;
    #FP;

    rst = 0;
    X = 2;
    Y = 0;
    enter = 0;
    #FP;

    rst = 0;
    X = 0;
    Y = 0;
    enter = 0;
    #FP;
    
    rst = 0;
    X = 0;
    Y = 0;
    enter = 1;
    #FP;

    rst = 0;
    X = 1;
    Y = 2;
    enter = 1;
    #FP;

    rst = 0;
    X = 1;
    Y = 2;
    enter = 0;
    #FP;




 

    $display("Simulation finished.");
    $finish(); // End the simulation
  end

endmodule

matrixops_tb.vcd
$date
	Mon Dec 09 22:52:11 2024
$end
$version
	Icarus Verilog
$end
$timescale
	1s
$end
$scope module matrixops_tb $end
$var wire 1 ! Z $end
$var parameter 64 " FP $end
$var parameter 32 # HP $end
$var reg 2 $ X [1:0] $end
$var reg 2 % Y [1:0] $end
$var reg 1 & clk $end
$var reg 1 ' enter $end
$var reg 1 ( rst $end
$scope module dut $end
$var wire 2 ) X [1:0] $end
$var wire 2 * Y [1:0] $end
$var wire 1 & clk $end
$var wire 1 ' enter $end
$var wire 1 ( rst $end
$var wire 4 + prev_idx [3:0] $end
$var wire 4 , index [3:0] $end
$var parameter 2 - IDLE $end
$var parameter 2 . in $end
$var parameter 2 / out $end
$var reg 1 ! Z $end
$var reg 3 0 cnt [2:0] $end
$var reg 4 1 ent_cnt [3:0] $end
$var reg 16 2 matrix [15:0] $end
$var reg 2 3 prev_X [1:0] $end
$var reg 2 4 prev_Y [1:0] $end
$var reg 1 5 prev_Z $end
$var reg 1 6 prev_ent $end
$var reg 2 7 state [1:0] $end
$upscope $end
$upscope $end
$enddefinitions $end
$comment Show the parameter values. $end
$dumpall
b10 /
b1 .
b0 -
b101 #
b1010 "
$end
#0
$dumpvars
b0 7
x6
x5
bx 4
bx 3
b0 2
b0 1
b0 0
b0 ,
bx +
b0 *
b0 )
1(
0'
1&
b0 %
b0 $
0!
$end
#5
06
b0 3
b0 +
b0 4
0&
#9
1'
0(
#10
b1 1
1&
#15
16
0&
#19
0'
#20
b1 7
1&
#25
06
0&
#29
1'
b10 ,
b10 $
b10 )
#30
b10 1
b100 2
1&
#35
16
b10 +
b10 3
0&
#39
b1 %
b1 *
b101 ,
b1 $
b1 )
#40
b100100 2
b11 1
b1 0
1&
#45
b1 3
b101 +
b1 4
0&
#49
b1101 ,
b11 %
b11 *
#50
b10 0
b100 1
b10000000100100 2
1&
#55
b1101 +
b11 4
0&
#60
b101 1
b11 0
1&
#65
0&
#69
b1111 ,
b11 $
b11 )
#70
b100 0
b110 1
b1010000000100100 2
1&
#75
b1111 +
b11 3
0&
#79
b10 %
b10 *
b1000 ,
b0 $
b0 )
#80
b10 7
b111 1
b101 0
1&
#85
b0 3
b1000 +
b10 4
05
0&
#89
b1 %
b1 *
b101 ,
b1 $
b1 )
#90
b110 0
b1000 1
1&
#95
b1 3
b101 +
b1 4
0&
#99
0'
#100
1!
1&
#105
06
15
0&
#110
1&
#115
0&
#119
b0 %
b0 *
b10 ,
b10 $
b10 )
#120
1&
#125
b10 3
b10 +
b0 4
0&
#129
b0 ,
b0 $
b0 )
#130
1&
#135
b0 +
b0 3
0&
#139
1'
#140
b1001 1
b111 0
1&
#145
16
0&
#149
b10 %
b10 *
b1001 ,
b1 $
b1 )
#150
0!
b0 0
b1010 1
1&
#155
05
b1 3
b1001 +
b10 4
0&
#159
0'
#160
1&
#165
06
0&
